pygameinputs/Button.py
pygameinputs/Label.py
pygameinputs/Sliders.py
pygameinputs/TextBox.py
pygameinputs/__init__.py
pygameinputs-0.1.4.dist-info/LICENSE.md
pygameinputs-0.1.4.dist-info/METADATA
pygameinputs-0.1.4.dist-info/WHEEL
pygameinputs-0.1.4.dist-info/top_level.txt
pygameinputs-0.1.4.dist-info/RECORD
