Metadata-Version: 2.1
Name: pygameinputs
Version: 0.1.4
Summary: A package to add inputs that work with pygame
Home-page: https://captainorigami01.github.io/pygame-inputs/
Author: Archie Harrison
Author-email: aj.harrison04@gmail.com
Project-URL: GitHub, https://github.com/captainorigami01/pygame-inputs
Project-URL: Bug Tracker, https://github.com/captainorigami01/pygame-inputs/issues
Classifier: Development Status :: 3 - Alpha
Classifier: Programming Language :: Python :: 3
Classifier: License :: OSI Approved :: MIT License
Classifier: Operating System :: OS Independent
Classifier: Intended Audience :: Developers
Classifier: Natural Language :: English
Requires-Python: <4,>=3.6
License-File: LICENSE.md
Requires-Dist: pygame
